README.md
setup.py
invoice_conversion/__init__.py
invoice_conversion/invoice_pdf.py
invoice_conversion.egg-info/PKG-INFO
invoice_conversion.egg-info/SOURCES.txt
invoice_conversion.egg-info/dependency_links.txt
invoice_conversion.egg-info/requires.txt
invoice_conversion.egg-info/top_level.txt