Metadata-Version: 2.1
Name: invoice-conversion
Version: 1.0.0
Summary: A simple utility to convert Excel-based invoices to PDF format.
Home-page: https://github.com/apotitech/invoice_conversion
Author: Lionel Tchami
Author-email: lionel@apotitech.com
Project-URL: Bug Reports, https://github.com/apotitech/invoice_conversion/issues
Project-URL: Source, https://github.com/apotitech/invoice_conversion
Keywords: excel,pdf,invoice,invoice converter,invoice conversion
Classifier: Development Status :: 3 - Alpha
Classifier: Intended Audience :: Financial and Insurance Industry
Classifier: License :: OSI Approved :: MIT License
Classifier: Programming Language :: Python :: 3
Classifier: Programming Language :: Python :: 3.8
